LICENSE
README.md
package_info.json
setup.py
th2_grpc_codec/__init__.py
th2_grpc_codec/codec.proto
th2_grpc_codec/codec_pb2.py
th2_grpc_codec/codec_pb2.pyi
th2_grpc_codec/codec_pb2_grpc.py
th2_grpc_codec/py.typed
th2_grpc_codec.egg-info/PKG-INFO
th2_grpc_codec.egg-info/SOURCES.txt
th2_grpc_codec.egg-info/dependency_links.txt
th2_grpc_codec.egg-info/requires.txt
th2_grpc_codec.egg-info/top_level.txt