Metadata-Version: 2.4
Name: th2_grpc_codec
Version: 0.2.1
Summary: th2_grpc_codec
Home-page: https://github.com/th2-net/th2-grpc-codec
Author: TH2-devs
Author-email: th2-devs@exactprosystems.com
License: Apache License 2.0
Requires-Python: >=3.7
License-File: LICENSE
Requires-Dist: th2-grpc-common<5,>=4.7.4
Requires-Dist: mypy-protobuf<5,>=3.6
Dynamic: author
Dynamic: author-email
Dynamic: description
Dynamic: description-content-type
Dynamic: home-page
Dynamic: license
Dynamic: license-file
Dynamic: requires-dist
Dynamic: requires-python
Dynamic: summary
